aiwenSDK/__init__.py
aiwenSDK/awEnum/CoordSys.py
aiwenSDK/awEnum/MultiFlag.py
aiwenSDK/awEnum/SceneLang.py
aiwenSDK/awEnum/StreetSubType.py
aiwenSDK/awEnum/__init__.py
aiwenSDK/awException/__init__.py
aiwenSDK/awException/aiwenException.py
aiwenSDK/awModel/__init__.py
aiwenSDK/awModel/aiwenKey.py
aiwenSDK/awModel/aiwenModels.py
aiwenSDK/client/__init__.py
aiwenSDK/client/aiwenClient.py
aiwenSDK-1.0.6.dist-info/METADATA
aiwenSDK-1.0.6.dist-info/WHEEL
aiwenSDK-1.0.6.dist-info/top_level.txt
aiwenSDK-1.0.6.dist-info/RECORD
