Metadata-Version: 2.1
Name: aiwenSDK
Version: 1.0.6
Summary: 对埃文商业API的网络请求的封装，方便调用
Home-page: https://www.ipplus360.com
Author: aiwen
Author-email: sales@ipplus360.com
License: UNKNOWN
Platform: UNKNOWN
Requires-Python: >=3.6
